panqake/__init__.py
panqake/__main__.py
panqake/cli.py
panqake/commands/__init__.py
panqake/commands/delete.py
panqake/commands/down.py
panqake/commands/list.py
panqake/commands/merge.py
panqake/commands/modify.py
panqake/commands/new.py
panqake/commands/pr.py
panqake/commands/rename.py
panqake/commands/submit.py
panqake/commands/switch.py
panqake/commands/sync.py
panqake/commands/track.py
panqake/commands/untrack.py
panqake/commands/up.py
panqake/commands/update.py
panqake/ports/__init__.py
panqake/ports/exceptions.py
panqake/ports/helpers.py
panqake/ports/implementations.py
panqake/ports/protocols.py
panqake/ports/results.py
panqake/testing/__init__.py
panqake/testing/fakes.py
panqake/utils/__init__.py
panqake/utils/branch_operations.py
panqake/utils/config.py
panqake/utils/exit.py
panqake/utils/git.py
panqake/utils/github.py
panqake/utils/questionary_prompt.py
panqake/utils/selection.py
panqake/utils/stack.py
panqake/utils/status.py
panqake/utils/types.py
panqake-0.26.0.dist-info/METADATA
panqake-0.26.0.dist-info/WHEEL
panqake-0.26.0.dist-info/entry_points.txt
panqake-0.26.0.dist-info/licenses/LICENSE
panqake-0.26.0.dist-info/RECORD
