Metadata-Version: 2.4
Name: panqake
Version: 0.26.0
Summary: CLI for git stacking
License-File: LICENSE
Requires-Python: >=3.12
Requires-Dist: prompt-toolkit>=3.0.51
Requires-Dist: questionary>=2.1.0
Requires-Dist: rich>=14.0.0
Requires-Dist: typer>=0.16.0
